{
	"id": 112102,
	"name": "Phán Quyết Công Bằng",
	"statustypetext": "Trạng Thái Nhân Vật",
	"cardtype": "GCG_CARD_STATE",
	"cardtypetext": "Trạng Thái",
	"tags": [],
	"description": "Khi nhân vật này hành động lần sau, trực tiếp dùng kỹ năng: Phán Quyết Công Bằng.",
	"descriptionraw": "Khi nhân vật này hành động lần sau, trực tiếp dùng kỹ năng: <color=#FFFFFFFF>$[S12104]</color>.",
	"descriptionreplaced": "Khi nhân vật này hành động lần sau, trực tiếp dùng kỹ năng: <color=#FFFFFFFF>Phán Quyết Công Bằng</color>."
}