{
	"name": "Núcleo Fúngico Adormecido",
	"description": "Tecido orgânico deixado para trás por um Fungo que foi exposto a intensos estímulos elementais.\nUma vez, houve um longo debate entre os pesquisadores Amurta sobre se os fungos deveriam ser categorizados como plantas ou animais. No final, eles chegaram a um acordo e encerraram definitivamente o caso — os Fungos devem ser sua própria categoria, nem vegetal e nem animal.",
	"sortorder": 2948,
	"rarity": "3",
	"category": "AVATAR_MATERIAL",
	"materialtype": "Material de Fortalecimento de Arma e Personagem",
	"source": [
		"Obtido na síntese"
	]
}