{
	"name": "Filosofia de Poemas",
	"description": "Material de Elevação de Talento.\nPoesia é a alma do Reino do Vento.\nPoesia é a manifestação do desejo de difundir as palavras. Embora nada seja eterno, ainda que nada seja o mesmo, a poesia do vento ainda se espalhará além dos céus, da terra e dos mares em todos os cantos do mundo.",
	"sortorder": 3223,
	"rarity": "4",
	"category": "AVATAR_MATERIAL",
	"materialtype": "Material de Talento do Personagem",
	"dropdomain": "Domínio da Proficiência: Reino do Sono",
	"daysofweek": [
		"Quarta-feira",
		"Sábado",
		"Domingo"
	],
	"source": [
		"Obtido na síntese"
	]
}