{
	"id": 216091,
	"name": "오색 염색",
	"statustypetext": "캐릭터 장비",
	"cardtype": "GCG_CARD_MODIFY",
	"cardtypetext": "장비 카드",
	"tags": [
		"GCG_TAG_TALENT",
		"GCG_TAG_SLOWLY"
	],
	"description": "해당 카드를 장착한 치오리가 하소데의 손길 사용 시: 추가로 평온한 마음의 타모토를 1개 소환하고, 4개의 치오리의 자동제어 인형 중에서 1개를 선정해 소환하는 것으로 변경된다.",
	"descriptionraw": "해당 카드를 장착한 $[A1609]가 <color=#FFFFFFFF>$[S16092]</color> 사용 시: 추가로 <color=#FFFFFFFF>$[C116094]</color>를 1개 소환하고, 4개의 <color=#FFFFFFFF>$[C116097]</color> 중에서 1개를 $[K59]해 소환하는 것으로 변경된다.",
	"descriptionreplaced": "해당 카드를 장착한 치오리가 <color=#FFFFFFFF>하소데의 손길</color> 사용 시: 추가로 <color=#FFFFFFFF>평온한 마음의 타모토</color>를 1개 소환하고, 4개의 <color=#FFFFFFFF>치오리의 자동제어 인형</color> 중에서 1개를 <color=#FFFFFFFF>선정</color>해 소환하는 것으로 변경된다."
}