{
	"id": [
		82291,
		82292,
		82293
	],
	"name": "\"Tupu'nun Bereketi\"",
	"achievementGroupId": 61,
	"achievementGroupName": "Düellocu: III. Seri",
	"sortOrder": 2291,
	"stages": 3,
	"stage1": {
		"title": "\"Tupu'nun Bereketi\"",
		"description": "Yerel Efsane: Tupu'nun Bereketini yen.",
		"progress": 1,
		"reward": {
			"id": 201,
			"name": "Köken Taşı",
			"count": 5
		}
	},
	"stage2": {
		"title": "\"Tupu'nun Bereketi\"",
		"description": "Bir mücadele sırasında hiçbir karakter saf dışı kalmamalı.",
		"progress": 1,
		"reward": {
			"id": 201,
			"name": "Köken Taşı",
			"count": 10
		}
	},
	"stage3": {
		"title": "\"Tupu'nun Bereketi\"",
		"description": "Bir mücadele sırasında Tupu'nun Bereketi tarafından oluşturulan Elektrik Tılsımının maksimum değerinin yarısından fazlasına ulaşmasına izin verme.",
		"progress": 1,
		"reward": {
			"id": 201,
			"name": "Köken Taşı",
			"count": 20
		}
	}
}