{
	"id": 3901,
	"name": "디오나",
	"c1": {
		"name": "칵테일의 여운",
		"descriptionRaw": "<color=#FFD780FF>특제 칵테일</color>의 효과 종료 후 디오나의 원소 에너지를 15pt 회복한다",
		"description": "특제 칵테일의 효과 종료 후 디오나의 원소 에너지를 15pt 회복한다"
	},
	"c2": {
		"name": "꽁꽁젤리 쉐이큰",
		"descriptionRaw": "<color=#FFD780FF>꽁꽁젤리</color>로 주는 피해가 15% 증가하고 보호막 피해 흡수량이 15% 증가한다.\n또한 꽁꽁젤리 명중 시 필드 주변의 다른 캐릭터에게도 피해 흡수량이 <color=#FFD780FF>꽁꽁젤리</color>의 50%인 보호막이 생성된다. 지속 시간: 5초",
		"description": "꽁꽁젤리로 주는 피해가 15% 증가하고 보호막 피해 흡수량이 15% 증가한다.\n또한 꽁꽁젤리 명중 시 필드 주변의 다른 캐릭터에게도 피해 흡수량이 꽁꽁젤리의 50%인 보호막이 생성된다. 지속 시간: 5초"
	},
	"c3": {
		"name": "한, 한 잔 더?",
		"descriptionRaw": "<color=#FFD780FF>특제 칵테일</color>의 스킬 레벨+3\n최대 Lv.15까지 상승",
		"description": "특제 칵테일의 스킬 레벨+3\n최대 Lv.15까지 상승"
	},
	"c4": {
		"name": "주류업 킬러",
		"descriptionRaw": "<color=#FFD780FF>특제 칵테일</color> 영역 내에서 디오나의 조준 사격 차지 시간이 60% 감소한다",
		"description": "특제 칵테일 영역 내에서 디오나의 조준 사격 차지 시간이 60% 감소한다"
	},
	"c5": {
		"name": "투 샷, 더블 아이스",
		"descriptionRaw": "<color=#FFD780FF>꽁꽁젤리</color>의 스킬 레벨+3\n최대 Lv.15까지 상승",
		"description": "꽁꽁젤리의 스킬 레벨+3\n최대 Lv.15까지 상승"
	},
	"c6": {
		"name": "캣테일 마감시간",
		"descriptionRaw": "<color=#FFD780FF>특제 칵테일</color> 영역 내의 캐릭터는 HP에 따라 아래의 효과를 갖는다:\n·HP 50% 이하 - 받는 치유 보너스+30%\n·HP 50% 초과 - 원소 마스터리+200pt",
		"description": "특제 칵테일 영역 내의 캐릭터는 HP에 따라 아래의 효과를 갖는다:\n·HP 50% 이하 - 받는 치유 보너스+30%\n·HP 50% 초과 - 원소 마스터리+200pt"
	}
}