{
	"id": 10000038,
	"name": "Woodland Dream",
	"rarity": 3,
	"foodtype": "SPECIALTY",
	"filterType": "COOK_FOOD_DEFENSE",
	"filterText": "เมนูการป้องกัน",
	"effect": "เพิ่มประสิทธิภาพโล่ป้องกัน ให้กับสมาชิกในทีมทั้งหมดขึ้น 35% เป็นเวลา 300 วินาที เมื่อเล่นในโหมดเล่นหลายคน จะมีผลกับตัวละครของตัวเองเท่านั้น",
	"description": "เมนูพิเศษของ Albedo ผักและผลไม้หลากหลายชนิดถูกจัดวางให้เป็นเหมือนทุ่งหญ้าและตั้งราวกับต้นไม้ อาหารจานนี้เป็นเหมือนเมืองที่ถูกห้อมล้อมด้วยกำแพง และมีเส้นทางสีน้ำตาลที่นำไปจนถึงปราสาทสีส้มอ่อน รสชาติที่ละเอียดอ่อนและหอมหวานราวกับดอกไม้ที่ผลิบานในชั่วพริบตา และเมื่อลืมตาขึ้นมาคุณจะรอยยิ้มในดวงตาของเจ้าชายผมขาว",
	"baseDishId": 3012,
	"baseDishName": "Sunshine Sprat",
	"characterId": 10000038,
	"characterName": "Albedo",
	"ingredients": [
		{
			"id": 110004,
			"name": "Butter",
			"count": 3
		},
		{
			"id": 100084,
			"name": "Fish",
			"count": 3
		},
		{
			"id": 100075,
			"name": "Salt",
			"count": 1
		},
		{
			"id": 100055,
			"name": "Small Lamp Grass",
			"count": 1
		}
	]
}