{
	"id": 10000106,
	"name": "Inno della Fiamma raccolta",
	"rarity": 3,
	"foodtype": "SPECIALTY",
	"filterType": "COOK_FOOD_ATTACK",
	"filterText": "Piatto ATT+",
	"effect": "Aumenta di un 20% il tasso di CRIT e i DAN da CRIT di tutti i membri del gruppo per 300 s. In modalità cooperativa, si applica solo ai tuoi personaggi.",
	"description": "La specialità di Mavuika. Una varietà di frutti di mare, tutti perfettamente grigliati, che si armonizza in una squisita sinfonia di sapori. Sembra un inno eterno e nobile che risuona nelle orecchie, con le fiamme inestinguibili che si accendono al ritmo dei morsi. La melodia che si ode racchiude una fonte di ispirazione. Forse anche questo fa parte dell'immensa forza dell'Archon di Pyro?",
	"baseDishId": 3510,
	"baseDishName": "Ode al magma",
	"characterId": 10000106,
	"characterName": "Mavuika",
	"ingredients": [
		{
			"id": 101243,
			"name": "Granifrutto",
			"count": 4
		},
		{
			"id": 100080,
			"name": "Patata",
			"count": 2
		},
		{
			"id": 100076,
			"name": "Cipolla",
			"count": 2
		},
		{
			"id": 100084,
			"name": "Pesce",
			"count": 2
		}
	]
}