{
	"name": "Panzerkrabbe",
	"specialname": "Im Fontemer entwickeltes Leben",
	"enemytype": "COMMON",
	"category": "Mystische Bestien",
	"description": "Eine Krabbe, die in Schneckenhäusern und anderen Gehäusen lebt.\nSie besitzt nahezu keinerlei Aggressivität, wie sie für Wildtiere typisch ist, da diese Aggressivität abgesehen vom Nahrungstrieb zumeist auf das Territorialverhalten eines Tiers zurückgeht, während das Revier der Panzerkrabbe ihr kleines Zuhause ist, das sie stets auf dem Rücken mit sich herumträgt.",
	"investigation": {
		"name": "Fontemer-Mutant",
		"category": "Normal",
		"description": "Wassertiere, die überall in Fontaine zu finden sind.\\nAufgrund ihrer spezifischen Ansprüche an die Natur leben sie offenbar nur in Fontaine."
	},
	"rewardpreview": [
		{
			"name": "Mora"
		},
		{
			"name": "Transozeanische Perle",
			"count": 0.8404
		},
		{
			"name": "Transozeanischer Brocken",
			"count": 0.2241
		},
		{
			"name": "Xenochromatischer Kristall",
			"count": 0.056
		}
	]
}