{
	"id": [
		80442,
		80443,
		80444
	],
	"name": "月尘的寻宝者·其一",
	"achievementGroupId": 63,
	"achievementGroupName": "挪德卡莱·月与浪迹的乐园·其之一",
	"sortOrder": 405,
	"stages": 3,
	"stage1": {
		"title": "月尘的寻宝者·其一",
		"ps5title": "月尘的寻宝者·其之一",
		"description": "在伦波岛、希汐岛、帕哈岛开启{param0}个宝箱。",
		"progress": 60,
		"reward": {
			"id": 201,
			"name": "原石",
			"count": 5
		}
	},
	"stage2": {
		"title": "月尘的寻宝者·其一",
		"ps5title": "月尘的寻宝者·其之二",
		"description": "在伦波岛、希汐岛、帕哈岛开启{param0}个宝箱。",
		"progress": 120,
		"reward": {
			"id": 201,
			"name": "原石",
			"count": 10
		}
	},
	"stage3": {
		"title": "月尘的寻宝者·其一",
		"ps5title": "月尘的寻宝者·其之三",
		"description": "在伦波岛、希汐岛、帕哈岛开启{param0}个宝箱。",
		"progress": 240,
		"reward": {
			"id": 201,
			"name": "原石",
			"count": 20
		}
	}
}