{
	"id": 1510,
	"name": "Xianyun",
	"shareid": 408,
	"hp": 10,
	"maxenergy": 2,
	"tags": [
		"GCG_TAG_ELEMENT_ANEMO",
		"GCG_TAG_WEAPON_CATALYST",
		"GCG_TAG_NATION_LIYUE"
	],
	"tagstext": [
		"ธาตุลม",
		"สื่อเวท",
		"Liyue"
	],
	"storytitle": "ปักษาสื่อสวรรค์ - Xianyun",
	"storytext": "วีรสตรีในเงาเมฆา",
	"source": "ได้รับหลังจากเชิญ Xianyun ทำการดูเอลใน Cat's Tail และเอาชนะในระดับความยากฉันมิตร",
	"skills": [
		{
			"id": 15101,
			"name": "Word of Wind and Flower",
			"descriptionraw": "สร้าง$[D__KEY__ELEMENT] $[D__KEY__DAMAGE] หน่วย",
			"basedamage": 1,
			"baseelement": "GCG_ELEMENT_ANEMO",
			"descriptionreplaced": "สร้าง{SPRITE_PRESET#2105}<color=#80FFD7FF>ความเสียหายลม</color> 1 หน่วย",
			"description": "สร้างความเสียหายลม 1 หน่วย",
			"typetag": "GCG_SKILL_TAG_A",
			"type": "โจมตีปกติ",
			"playcost": [
				{
					"costtype": "GCG_COST_DICE_ANEMO",
					"count": 1
				},
				{
					"costtype": "GCG_COST_DICE_VOID",
					"count": 2
				}
			]
		},
		{
			"id": 15102,
			"name": "White Clouds at Dawn",
			"descriptionraw": "สร้าง$[D__KEY__ELEMENT] $[D__KEY__DAMAGE] หน่วย สร้าง <color=#FFFFFFFF>$[C115101]</color> และตัวละครนี้จะได้รับ <color=#FFFFFFFF>$[C115104]</color>",
			"basedamage": 2,
			"baseelement": "GCG_ELEMENT_ANEMO",
			"descriptionreplaced": "สร้าง{SPRITE_PRESET#2105}<color=#80FFD7FF>ความเสียหายลม</color> 2 หน่วย สร้าง <color=#FFFFFFFF>บันไดสุราลัย</color> และตัวละครนี้จะได้รับ <color=#FFFFFFFF>Driftcloud Wave</color>",
			"description": "สร้างความเสียหายลม 2 หน่วย สร้าง บันไดสุราลัย และตัวละครนี้จะได้รับ Driftcloud Wave",
			"typetag": "GCG_SKILL_TAG_E",
			"type": "สกิลธาตุ",
			"playcost": [
				{
					"costtype": "GCG_COST_DICE_ANEMO",
					"count": 3
				}
			]
		},
		{
			"id": 15103,
			"name": "Stars Gather at Dusk",
			"descriptionraw": "สร้าง$[D__KEY__ELEMENT] $[D__KEY__DAMAGE] หน่วย รักษาตัวละครทั้งหมดของฝ่ายเรา 1 หน่วย และทำให้เกิดการ์ด <color=#FFFFFFFF>$[C115102]</color>\\n(ตัวละครที่ติดตั้งการ์ด <color=#FFFFFFFF>$[C115102]</color> สามารถใช้เทคนิค: <color=#FFFFFFFF>$[S1151021]</color>)",
			"basedamage": 1,
			"baseelement": "GCG_ELEMENT_ANEMO",
			"descriptionreplaced": "สร้าง{SPRITE_PRESET#2105}<color=#80FFD7FF>ความเสียหายลม</color> 1 หน่วย รักษาตัวละครทั้งหมดของฝ่ายเรา 1 หน่วย และทำให้เกิดการ์ด <color=#FFFFFFFF>Starwicker</color>\\n(ตัวละครที่ติดตั้งการ์ด <color=#FFFFFFFF>Starwicker</color> สามารถใช้เทคนิค: <color=#FFFFFFFF>Adeptal Assistance</color>)",
			"description": "สร้างความเสียหายลม 1 หน่วย รักษาตัวละครทั้งหมดของฝ่ายเรา 1 หน่วย และทำให้เกิดการ์ด Starwicker\n(ตัวละครที่ติดตั้งการ์ด Starwicker สามารถใช้เทคนิค: Adeptal Assistance)",
			"typetag": "GCG_SKILL_TAG_Q",
			"type": "ท่าไม้ตาย",
			"playcost": [
				{
					"costtype": "GCG_COST_DICE_ANEMO",
					"count": 3
				},
				{
					"costtype": "GCG_COST_ENERGY",
					"count": 2
				}
			]
		}
	]
}