{
	"name": "Klee",
	"title": "Sol Fugitivo",
	"description": "Uma visitante frequente da sala de confinamento dos Cavaleiros de Favonius, também conhecido como \"Sol Fugitivo\".",
	"rarity": "5",
	"element": "Pyro",
	"weapontype": "Catalisador",
	"substat": "Bônus de Dano Pyro",
	"gender": "FEMALE",
	"body": "LOLI",
	"association": "MONDSTADT",
	"region": "Mondstadt",
	"affiliation": "Cavaleiros de Favonius",
	"birthdaymmdd": "7/27",
	"birthday": "27 de julho",
	"constellation": "Trifolium",
	"images": {},
	"cv": {
		"english": "Poonam Basu",
		"chinese": "花玲",
		"japanese": "久野美咲",
		"korean": "방연지"
	},
	"talentmaterialtype": ""
}