{
	"name": "Binbir Gece Süzülen Rüyalar",
	"description": "Bu lamba binbir geceyi aşkındır süzülen rüyaları aydınlatır ve zümrüt yeşili ışığında kadim günlerin bir şarkısı yankılanır.",
	"weapontype": "Katalizör",
	"rarity": "5",
	"baseatk": 44,
	"substat": "Element Ustalığı",
	"subvalue": "58",
	"effectname": "Binbir Gecenin Şafağı Şarkısı",
	"effect": "Kuşanan karakter dışındaki grup üyeleri, Element Türlerinin kuşanan karakterle aynı olup olmamasına bağlı olarak kuşanan karaktere güçlendirme sağlarlar. Element Türleri aynıysa kuşanan karakterin Element Ustalığı {0} artar. Aynı değilse kuşanan karakterin Element Türüne ait Element Hasarı Bonusu {1} artar. Bu etkiler 3 kademeye kadar birikebilir. Ayrıca, kuşanan karakter dışında yakında bulunan tüm grup üyelerinin Element Ustalığı {2} artar. Aynı silahtan birden fazla olması durumunda bu etkiler birikebilir.",
	"r1": [
		"32",
		"%10",
		"40"
	],
	"r2": [
		"40",
		"%14",
		"42"
	],
	"r3": [
		"48",
		"%18",
		"44"
	],
	"r4": [
		"56",
		"%22",
		"46"
	],
	"r5": [
		"64",
		"%26",
		"48"
	],
	"weaponmaterialtype": "",
	"costs": {
		"ascend1": [
			{
				"name": "Mora",
				"count": 10000
			},
			{
				"name": "Vaha Bahçesi Hatırası",
				"count": 5
			},
			{
				"name": "Hasarlı Prizma",
				"count": 5
			},
			{
				"name": "Mantar Sporları",
				"count": 3
			}
		],
		"ascend2": [
			{
				"name": "Mora",
				"count": 20000
			},
			{
				"name": "Vaha Bahçesi Zarafeti",
				"count": 5
			},
			{
				"name": "Hasarlı Prizma",
				"count": 18
			},
			{
				"name": "Mantar Sporları",
				"count": 12
			}
		],
		"ascend3": [
			{
				"name": "Mora",
				"count": 30000
			},
			{
				"name": "Vaha Bahçesi Zarafeti",
				"count": 9
			},
			{
				"name": "Bulanık Prizma",
				"count": 9
			},
			{
				"name": "Parlak Polen",
				"count": 9
			}
		],
		"ascend4": [
			{
				"name": "Mora",
				"count": 45000
			},
			{
				"name": "Vaha Bahçesi Matemi",
				"count": 5
			},
			{
				"name": "Bulanık Prizma",
				"count": 18
			},
			{
				"name": "Parlak Polen",
				"count": 14
			}
		],
		"ascend5": [
			{
				"name": "Mora",
				"count": 55000
			},
			{
				"name": "Vaha Bahçesi Matemi",
				"count": 9
			},
			{
				"name": "Parlak Prizma",
				"count": 14
			},
			{
				"name": "Kristal Toz Kutusu",
				"count": 9
			}
		],
		"ascend6": [
			{
				"name": "Mora",
				"count": 65000
			},
			{
				"name": "Vaha Bahçesi Gerçeği",
				"count": 6
			},
			{
				"name": "Parlak Prizma",
				"count": 27
			},
			{
				"name": "Kristal Toz Kutusu",
				"count": 18
			}
		]
	}
}