{
	"id": 28020601,
	"name": "Schneemarder",
	"description": "Schlanke und geschickte Schlingel, die gern böse Streiche spielen.\nDiese Marder verstecken sich in Löchern auf den schneebedeckten Ebenen und huschen dort unbemerkt durch die Gegend. Im Normalfall jagen sie Ungeziefer und kleine Eidechsen. Vor Tieren, die ein wenig größer sind als sie selbst, schrecken sie aber auch nicht zurück. Hin und wieder versuchen Menschen, die sie niedlich finden, sie einzufangen, um sie als Haustiere zu halten. Doch da sie ihre Freiheit lieben, lassen sie sich nur schwer vom heimischen Glück der Menschen überzeugen.",
	"categoryType": "SUBTYPE_ANIMAL",
	"categoryText": "Landgänger",
	"countType": "COUNT_TYPE_CAPTURE",
	"sortOrder": 11029
}