{
	"id": 101010,
	"name": "Regenbogen-Kristall",
	"sortRank": 301,
	"description": "Ein in schillerndem Regenbogenglanz leuchtender Kristall mit außergewöhnlicher Zähigkeit und Formbarkeit. Seit jeher ist er das bevorzugte Schmiedematerial der Handwerker Snezhnayas.\nMan erzählt sich, als der hohe Wagen des Mondes zerbrach, stürzte seine mit göttlichem Blut getränkte Radnabe in die mondbeschienene Welt hinab und wurde zu einem regenbogenfarbenen Juwel. Seitdem bringen die Menschen den gefallenen Göttern keinen Glauben mehr entgegen. Nur die wenigen Überlebenden, die wissen, weshalb die Könige der Nacht starben, singen weiter ihre vergessenen Namen, vergeblich.",
	"category": "EXCHANGE",
	"typeText": "Zum Schmieden geeignetes Erz",
	"sources": [
		"In der freien Natur zu finden"
	]
}