{
	"id": [
		82244,
		82245,
		82246
	],
	"name": "«Тень Чимальи»",
	"achievementGroupId": 54,
	"achievementGroupName": "Дуэлянт I",
	"sortOrder": 2244,
	"stages": 3,
	"stage1": {
		"title": "«Тень Чимальи»",
		"description": "Победите местную легенду, Тень Чимальи.",
		"progress": 1,
		"reward": {
			"id": 201,
			"name": "Камень Истока",
			"count": 5
		}
	},
	"stage2": {
		"title": "«Тень Чимальи»",
		"description": "Победите Тень Чимальи, не потеряв ни одного персонажа.",
		"progress": 1,
		"reward": {
			"id": 201,
			"name": "Камень Истока",
			"count": 10
		}
	},
	"stage3": {
		"title": "«Тень Чимальи»",
		"description": "В ходе выполнения одного задания, когда Тень Чимальи поглощает создания потока, разрушьте её элементальный щит, выпустив замороженных созданий потока.",
		"progress": 1,
		"reward": {
			"id": 201,
			"name": "Камень Истока",
			"count": 20
		}
	}
}