{
	"id": 10000112,
	"name": "드보르 케이크·호화판",
	"rarity": 4,
	"foodtype": "SPECIALTY",
	"filterType": "COOK_FOOD_ATTACK",
	"filterText": "공격류 요리",
	"effect": "파티 내 모든 캐릭터의 공격력이 384pt, 치명타 확률이 14% 증가한다. 지속 시간: 300초. 다인 모드 시 자신의 캐릭터에만 적용된다",
	"description": "에스코피에의 특제 요리. 지금까지 본 어떤 케이크보다 더 호화로운 작품. 한눈에 사람을 사로잡는 마력을 가진 이 케이크는 맛까지 완벽하다. 부드럽고 따뜻한 맛이 포근한 이불처럼 미뢰를 감싸며 행복감을 불러일으킨다…. 에스코피에의 요리 실력이 어느새 한층 더 발전했다는 사실은 의심의 여지가 없다",
	"baseDishId": 4404,
	"baseDishName": "드보르 미니 케이크·개량형",
	"characterId": 10000112,
	"characterName": "에스코피에",
	"ingredients": [
		{
			"id": 101233,
			"name": "바다 이슬 꽃",
			"count": 3
		},
		{
			"id": 100062,
			"name": "새알",
			"count": 3
		},
		{
			"id": 110001,
			"name": "밀가루",
			"count": 2
		},
		{
			"id": 110002,
			"name": "크림",
			"count": 2
		}
	]
}