{
	"name": "Lôi Minh Tiên",
	"description": "Loài cá bướm quý hiếm ở Inazuma, thích tụ tập ở những vùng nước có nguyên tố lôi.\nTương truyền nguồn gốc của loài cá này là \"Trường Sinh Tiên\" của Liyue, được các thương lái du nhập đến Inazuma và thích nghi với điều kiện sống nơi này. Hiện nay đã có học giả dùng nó và Slime Lôi để nghiên cứu về điện.\n\"Tê... tê... đầu lưỡi... tê quá\" - Một thực khách bình luận.",
	"sortorder": 2863,
	"rarity": "3",
	"category": "EXCHANGE",
	"materialtype": "Cá",
	"source": [
		"Câu cá nhận được"
	]
}