{
	"id": 20070101,
	"name": "雷音權現",
	"specialName": "霆雷的忿恨意志",
	"enemyType": "BOSS",
	"category": "元素生命",
	"description": "異常的雷元素生命。雖然外貌上與純水精靈有相似之處，卻不具備她的智慧與記憶。\n驅動雷音權現的是更為原始純粹的憤怒。\n據說這種生物只會隨著雷霆降生在遺留著強大忿恨的地方，譬如說支離破碎、雷雲黝黝的天雲峠。只要土地中的怨恨不消，那雷鳴也不會斷絕吧。",
	"investigation": {
		"name": "雷音權現",
		"category": "首領",
		"description": "異常的雷元素生命，以電光與霆雷高唱驅使它行動的忿恨。\\n雖然形象上與「純水精靈」有著某種程度上的相似之處，但似乎並不具備純水精靈的智慧。\\n傳說是由純粹的悔恨驅使的元素魔物。",
		"lockdesc": "天雲峠的風暴中，傳來了憤怒的雷鳴…"
	},
	"rewardPreview": [
		{
			"id": 102,
			"name": "冒險閱歷",
			"count": 200
		},
		{
			"id": 202,
			"name": "摩拉"
		},
		{
			"id": 105,
			"name": "好感經驗"
		},
		{
			"id": 113029,
			"name": "雷霆數珠",
			"count": 2.5556
		},
		{
			"id": 104141,
			"name": "最勝紫晶碎屑"
		},
		{
			"id": 104142,
			"name": "最勝紫晶斷片"
		},
		{
			"id": 104143,
			"name": "最勝紫晶塊"
		},
		{
			"id": 104144,
			"name": "最勝紫晶"
		},
		{
			"id": 400032,
			"name": "教官",
			"rarity": 3
		},
		{
			"id": 400042,
			"name": "流放者",
			"rarity": 3
		},
		{
			"id": 400137,
			"name": "祭雷之人",
			"rarity": 3
		},
		{
			"id": 400062,
			"name": "遊醫",
			"rarity": 3
		},
		{
			"id": 400088,
			"name": "角鬥士的終幕禮",
			"rarity": 4
		},
		{
			"id": 400098,
			"name": "流浪大地的樂團",
			"rarity": 4
		},
		{
			"id": 400033,
			"name": "教官",
			"rarity": 4
		},
		{
			"id": 400043,
			"name": "流放者",
			"rarity": 4
		},
		{
			"id": 400138,
			"name": "祭雷之人",
			"rarity": 4
		},
		{
			"id": 400089,
			"name": "角鬥士的終幕禮",
			"rarity": 5
		},
		{
			"id": 400099,
			"name": "流浪大地的樂團",
			"rarity": 5
		}
	]
}