{
	"id": 1003,
	"name": "Trứng Chiên Teyvat",
	"rarity": 1,
	"foodtype": "NORMAL",
	"filterType": "COOK_FOOD_HEAL",
	"filterText": "Món Dạng Hồi Phục",
	"effect": "Hồi sinh cho nhân vật được chọn.\nHồi 50-150 điểm HP.",
	"description": "Trứng chiên chín một mặt. Lòng đỏ còn mọng nước, rất thơm ngon.",
	"suspicious": {
		"effect": "Hồi 50 điểm HP cho nhân vật được chọn hồi sinh.",
		"description": "Trứng chiên chín một mặt. Ăn hơi cứng, hy vọng chất dinh dưỡng không bị mất đi."
	},
	"normal": {
		"effect": "Hồi 100 điểm HP cho nhân vật được chọn hồi sinh.",
		"description": "Trứng chiên chín một mặt. Lòng đỏ còn mọng nước, rất thơm ngon."
	},
	"delicious": {
		"effect": "Hồi 150 điểm HP cho nhân vật được chọn hồi sinh.",
		"description": "Trứng chiên chín một mặt. Có mùi vị ấm áp như mặt trời, cắn một miếng sẽ như có thêm sức mạnh."
	},
	"ingredients": [
		{
			"id": 100062,
			"name": "Trứng Chim",
			"count": 1
		}
	]
}